{
  "BANANAS31": {
    "last_updated": "2025-11-20 00:33:15",
    "long_short_ratio": 1.21,
    "open_interest": 10710623.1906,
    "price": 0.002673,
    "top_account_ratio": 1.47,
    "top_position_ratio": 1.22
  },
  "PLAY": {
    "last_updated": "2025-11-20 00:32:01",
    "long_short_ratio": 1.74,
    "open_interest": 2568919.5622,
    "price": 0.02879,
    "top_account_ratio": 1.55,
    "top_position_ratio": 1.85
  },
  "PORT3": {
    "last_updated": "2025-11-20 00:32:08",
    "long_short_ratio": 0.89,
    "open_interest": 23378709.7559,
    "price": 0.03517,
    "top_account_ratio": 0.88,
    "top_position_ratio": 0.47
  },
  "SKYAI": {
    "last_updated": "2025-11-20 00:33:08",
    "long_short_ratio": 1.135,
    "open_interest": 8716652.6571,
    "price": 0.02147,
    "top_account_ratio": 1.06,
    "top_position_ratio": 1.55
  },
  "SOLV": {
    "last_updated": "2025-11-20 00:32:14",
    "long_short_ratio": 0.62,
    "open_interest": 19242369.3999,
    "price": 0.01633,
    "top_account_ratio": 0.73,
    "top_position_ratio": 1.45
  },
  "TAG": {
    "last_updated": "2025-11-20 00:33:02",
    "long_short_ratio": 1.52,
    "open_interest": 5071155.6044,
    "price": 0.0005291,
    "top_account_ratio": 1.38,
    "top_position_ratio": 1.63
  }
}