{
  "BANANAS31": {
    "last_updated": "2025-11-20 09:50:32",
    "long_short_ratio": 1.375,
    "open_interest": 10437937.2458,
    "price": 0.002742,
    "top_account_ratio": 1.38,
    "top_position_ratio": 1.28
  },
  "PLAY": {
    "last_updated": "2025-11-20 09:51:19",
    "long_short_ratio": 1.74,
    "open_interest": 2628041.26,
    "price": 0.02916,
    "top_account_ratio": 1.58,
    "top_position_ratio": 1.85
  },
  "PORT3": {
    "last_updated": "2025-11-20 09:51:25",
    "long_short_ratio": 0.91,
    "open_interest": 23014538.933,
    "price": 0.03494,
    "top_account_ratio": 0.9,
    "top_position_ratio": 0.48
  },
  "SKYAI": {
    "last_updated": "2025-11-20 09:50:26",
    "long_short_ratio": 1.17,
    "open_interest": 8665966.0527,
    "price": 0.02236,
    "top_account_ratio": 1.01,
    "top_position_ratio": 1.45
  },
  "SOLV": {
    "last_updated": "2025-11-20 09:51:31",
    "long_short_ratio": 0.66,
    "open_interest": 18678452.5,
    "price": 0.01625,
    "top_account_ratio": 0.78,
    "top_position_ratio": 1.42
  },
  "TAG": {
    "last_updated": "2025-11-20 09:50:19",
    "long_short_ratio": 1.49,
    "open_interest": 5093679.5046,
    "price": 0.0005285,
    "top_account_ratio": 1.31,
    "top_position_ratio": 1.6
  }
}